Metadata-Version: 2.1
Name: permsekz
Version: 1.1.1
Summary: dangerous
Home-page: UNKNOWN
Author: NuatStanskiy
Author-email: smiril13@mail.ru
License: Apache License, Version 2.0, see LICENSE file
Platform: UNKNOWN
